repoze.profile-2.3-py3.6-nspkg.pth
repoze/profile/__init__.py
repoze/profile/compat.py
repoze/profile/decorator.py
repoze/profile/profiler.html
repoze/profile/profiler.py
repoze/profile/tests.py
repoze.profile-2.3.dist-info/LICENSE.txt
repoze.profile-2.3.dist-info/METADATA
repoze.profile-2.3.dist-info/WHEEL
repoze.profile-2.3.dist-info/entry_points.txt
repoze.profile-2.3.dist-info/namespace_packages.txt
repoze.profile-2.3.dist-info/top_level.txt
repoze.profile-2.3.dist-info/RECORD
